{"Afrikaans": [["spokenIn", "Namibia"], ["spokenIn", "South_Africa"], ["languageRegulator", "Die_Taalkommissie"], ["languageFamily", "West_Germanic_languages"], ["languageFamily", "Low_Franconian"], ["languageFamily", "Germanic_languages"], ["languageFamily", "Weser-Rhine_Germanic"]], "Bwile_language": [["spokenIn", "Democratic_Republic_of_the_Congo"], ["spokenIn", "Zambia"], ["languageFamily", "Bantu_languages"], ["languageFamily", "Southern_Bantoid_languages"], ["languageFamily", "Benue\u00e2\u0080\u0093Congo_languages"], ["languageFamily", "Atlantic\u00e2\u0080\u0093Congo_languages"]], "Dciriku_language": [["spokenIn", "Okavango_River"], ["languageFamily", "Bantu_languages"], ["languageFamily", "Southern_Bantoid_languages"], ["languageFamily", "Benue\u00e2\u0080\u0093Congo_languages"], ["languageFamily", "Atlantic\u00e2\u0080\u0093Congo_languages"]], "Fwe_language": [["spokenIn", "Zambezi_Region"], ["spokenIn", "Namibia"], ["spokenIn", "Zambia"], ["spokenIn", "Western_Province,_Zambia"], ["languageFamily", "Bantu_languages"], ["languageFamily", "Southern_Bantoid_languages"], ["languageFamily", "Benue\u00e2\u0080\u0093Congo_languages"], ["languageFamily", "Atlantic\u00e2\u0080\u0093Congo_languages"]], "German_language": [["soundRecording", "German_language__Sound__1"]], "German_language_in_Namibia": [["languageFamily", "West_Germanic_languages"], ["languageFamily", "Germanic_languages"], ["languageFamily", "High_German_languages"]], "Hakaona_language": [["spokenIn", "Angola"], ["spokenIn", "Namibia"], ["languageFamily", "Bantu_languages"], ["languageFamily", "Southern_Bantoid_languages"], ["languageFamily", "Benue\u00e2\u0080\u0093Congo_languages"], ["languageFamily", "Atlantic\u00e2\u0080\u0093Congo_languages"]], "Khoekhoe_language": [["spokenIn", "Orange_River"], ["spokenIn", "Botswana"], ["spokenIn", "Namibia"], ["spokenIn", "Damaraland"], ["spokenIn", "Namaqualand"], ["spokenIn", "South_Africa"], ["languageFamily", "Khoe_languages"]], "Khoemana": [["languageFamily", "Khoekhoe_language"], ["languageFamily", "Khoe_languages"]], "Kuhane_language": [["spokenIn", "Zambezi"], ["languageFamily", "Bantu_languages"], ["languageFamily", "Southern_Bantoid_languages"], ["languageFamily", "Benue\u00e2\u0080\u0093Congo_languages"], ["languageFamily", "Atlantic\u00e2\u0080\u0093Congo_languages"]], "Kwangali_language": [["spokenIn", "Okavango_River"], ["spokenIn", "Angola"], ["spokenIn", "Namibia"], ["languageFamily", "Volta\u00e2\u0080\u0093Congo_languages"], ["languageFamily", "Benue\u00e2\u0080\u0093Congo_languages"], ["languageFamily", "Bantoid_languages"], ["languageFamily", "Atlantic\u00e2\u0080\u0093Congo_languages"]], "Kwanyama_dialect": [["spokenIn", "Angola"], ["spokenIn", "Namibia"], ["spokenIn", "Ovamboland"], ["languageFamily", "Volta\u00e2\u0080\u0093Congo_languages"], ["languageFamily", "Benue\u00e2\u0080\u0093Congo_languages"], ["languageFamily", "Bantoid_languages"], ["languageFamily", "Atlantic\u00e2\u0080\u0093Congo_languages"]], "Lozi_language": [["spokenIn", "Botswana"], ["spokenIn", "Zambezi"], ["spokenIn", "Namibia"], ["spokenIn", "Zambia"], ["spokenIn", "Zimbabwe"], ["spokenIn", "South_Africa"], ["languageFamily", "Volta\u00e2\u0080\u0093Congo_languages"], ["languageFamily", "Benue\u00e2\u0080\u0093Congo_languages"], ["languageFamily", "Bantoid_languages"], ["languageFamily", "Atlantic\u00e2\u0080\u0093Congo_languages"]], "Luyana_language": [["spokenIn", "Okavango_River"], ["spokenIn", "Angola"], ["spokenIn", "Namibia"], ["spokenIn", "Zambia"], ["languageFamily", "Bantu_languages"], ["languageFamily", "Southern_Bantoid_languages"], ["languageFamily", "Benue\u00e2\u0080\u0093Congo_languages"], ["languageFamily", "Atlantic\u00e2\u0080\u0093Congo_languages"]], "Mbowe_language": [["spokenIn", "Okavango_River"], ["spokenIn", "Zambia"], ["languageFamily", "Bantu_languages"], ["languageFamily", "Southern_Bantoid_languages"], ["languageFamily", "Benue\u00e2\u0080\u0093Congo_languages"], ["languageFamily", "Atlantic\u00e2\u0080\u0093Congo_languages"]], "Mbukushu_language": [["spokenIn", "Okavango_River"], ["spokenIn", "Angola"], ["spokenIn", "Botswana"], ["spokenIn", "Namibia"], ["spokenIn", "Zambia"], ["languageFamily", "Bantu_languages"], ["languageFamily", "Southern_Bantoid_languages"], ["languageFamily", "Benue\u00e2\u0080\u0093Congo_languages"], ["languageFamily", "Atlantic\u00e2\u0080\u0093Congo_languages"]], "Mbunda_language": [["spokenIn", "Angola"], ["spokenIn", "Zambia"], ["languageFamily", "Volta\u00e2\u0080\u0093Congo_languages"], ["languageFamily", "Benue\u00e2\u0080\u0093Congo_languages"], ["languageFamily", "Bantoid_languages"], ["languageFamily", "Atlantic\u00e2\u0080\u0093Congo_languages"]], "Namibian_Black_German": [["spokenIn", "Namibia"]], "Namibian_Sign_Language": [["spokenIn", "Angola"], ["spokenIn", "Namibia"], ["languageFamily", "Paget_Gorman_Sign_System"]], "Sekele_language": [["spokenIn", "Kavango_Region"], ["spokenIn", "Angola"], ["spokenIn", "Namibia"], ["spokenIn", "Ovamboland"], ["languageFamily", "\u00c7\u0083Kung_languages"], ["languageFamily", "Kx\u00ca\u00bca_languages"]], "Tswana_language": [["spokenIn", "Botswana"], ["spokenIn", "South_Africa"], ["languageFamily", "Volta\u00e2\u0080\u0093Congo_languages"], ["languageFamily", "Benue\u00e2\u0080\u0093Congo_languages"], ["languageFamily", "Bantoid_languages"], ["languageFamily", "Atlantic\u00e2\u0080\u0093Congo_languages"]], "Ts\u00ca\u00bcixa_language": [["spokenIn", "Botswana"], ["languageFamily", "Khoe_languages"]], "Umbundu": [["spokenIn", "Angola"], ["languageFamily", "Volta\u00e2\u0080\u0093Congo_languages"], ["languageFamily", "Benue\u00e2\u0080\u0093Congo_languages"], ["languageFamily", "Bantoid_languages"], ["languageFamily", "Atlantic\u00e2\u0080\u0093Congo_languages"]], "Yeyi_language": [["spokenIn", "Okavango_River"], ["spokenIn", "Botswana"], ["spokenIn", "Namibia"], ["languageFamily", "Volta\u00e2\u0080\u0093Congo_languages"], ["languageFamily", "Benue\u00e2\u0080\u0093Congo_languages"], ["languageFamily", "Bantoid_languages"], ["languageFamily", "Atlantic\u00e2\u0080\u0093Congo_languages"]]}