{"104.6_RTL": [["broadcastArea", "Livestreaming"], ["broadcastArea", "Brandenburg"], ["broadcastArea", "Digital_Audio_Broadcasting"], ["broadcastArea", "Berlin"], ["city", "Berlin"], ["programmeFormat", "Adult_contemporary_music"]], "1LIVE": [["broadcastArea", "Internet"], ["broadcastArea", "DVB-C"], ["broadcastArea", "DVB-S"], ["broadcastArea", "Digital_Audio_Broadcasting"], ["broadcastArea", "North_Rhine-Westphalia"], ["city", "Cologne"], ["owner", "Westdeutscher_Rundfunk"], ["programmeFormat", "Popular_music"]], "89.0_RTL": [["broadcastArea", "Saxony"], ["broadcastArea", "Saxony-Anhalt"], ["broadcastArea", "Hesse"], ["broadcastArea", "Lower_Saxony"], ["broadcastArea", "Digital_Audio_Broadcasting"], ["broadcastArea", "Thuringia"], ["city", "Saxony-Anhalt"], ["owner", "RTL_Group"], ["programmeFormat", "Contemporary_hit_radio"]], "98.8_KISS_FM_Berlin": [["broadcastArea", "Brandenburg"], ["broadcastArea", "Digital_Audio_Broadcasting"], ["broadcastArea", "Berlin"], ["programmeFormat", "Rhythmic_contemporary"]], "Antenne_Brandenburg": [["broadcastArea", "Brandenburg"], ["broadcastArea", "Berlin"], ["language", "German_language"]], "BR-Klassik": [["broadcastArea", "Bavaria"], ["language", "German_language"]], "BR24": [["broadcastArea", "Bavaria"], ["language", "German_language"], ["programmeFormat", "All-news_radio"]], "BR24live": [["broadcastArea", "Bavaria"], ["language", "German_language"], ["programmeFormat", "All-news_radio"]], "BR_Heimat": [["broadcastArea", "Bavaria"], ["language", "German_language"]], "BR_Schlager": [["broadcastArea", "Bavaria"], ["language", "German_language"]], "BR_Verkehr": [["broadcastArea", "Bavaria"], ["language", "German_language"], ["programmeFormat", "Traffic_reporting"]], "Bayerischer_Rundfunk": [["broadcastNetwork", "ARD_(broadcaster)"], ["country", "Germany"], ["locationCountry", "Germany"]], "Bayern_1": [["broadcastArea", "Bavaria"], ["language", "German_language"]], "Bayern_2": [["broadcastArea", "Bavaria"], ["language", "German_language"]], "Bayern_3": [["broadcastArea", "Bavaria"], ["language", "German_language"]], "Beitragsservice_von_ARD,_ZDF_und_Deutschlandradio": [["industry", "Copyright_collective"], ["keyPerson", "Chief_executive_officer"], ["locationCity", "Cologne"], ["locationCity", "North_Rhine-Westphalia"], ["locationCountry", "Germany"], ["regionServed", "Germany"]], "BigFM": [["broadcastArea", "Baden-W\u00c3\u00bcrttemberg"], ["broadcastArea", "Saarland"], ["broadcastArea", "Rhineland-Palatinate"], ["programmeFormat", "Contemporary_hit_radio"]], "Bremen_Eins": [["broadcastArea", "Bremen_(state)"], ["language", "German_language"]], "Bremen_Next": [["broadcastArea", "Bremen_(state)"], ["language", "German_language"]], "Bremen_Vier": [["broadcastArea", "Bremen_(state)"], ["language", "German_language"]], "Bremen_Zwei": [["broadcastArea", "Bremen_(state)"], ["language", "German_language"]], "COSMO_(German_radio_station)": [["broadcastArea", "Brandenburg"], ["broadcastArea", "Bremen_(state)"], ["broadcastArea", "Berlin"], ["broadcastArea", "North_Rhine-Westphalia"], ["language", "German_language"]], "Delta_radio": [["broadcastArea", "Schleswig-Holstein"], ["broadcastArea", "Hamburg"], ["city", "Kiel"], ["programmeFormat", "Alternative_rock"]], "Deutschlandfunk": [["city", "Cologne"], ["language", "German_language"], ["owner", "Deutschlandradio"], ["programmeFormat", "News"], ["programmeFormat", "Speech"], ["sisterStation", "Deutschlandfunk_Kultur"], ["sisterStation", "Deutschlandradio"], ["sisterStation", "Deutschlandfunk_Nova"]], "Deutschlandfunk_Kultur": [["city", "Berlin"], ["language", "German_language"], ["owner", "Deutschlandradio"], ["programmeFormat", "Speech"], ["programmeFormat", "Culture"], ["sisterStation", "Deutschlandradio"], ["sisterStation", "Deutschlandfunk"], ["sisterStation", "Deutschlandfunk_Nova"]], "Deutschlandfunk_Nova": [["city", "Cologne"], ["language", "German_language"], ["owner", "Deutschlandradio"], ["programmeFormat", "Speech"], ["sisterStation", "Deutschlandfunk_Kultur"], ["sisterStation", "Deutschlandradio"], ["sisterStation", "Deutschlandfunk"]], "History_of_S\u00c3\u00bcdwestrundfunk": [["country", "Germany"], ["headquarter", "Baden-Baden"], ["headquarter", "Germany"], ["locationCountry", "Germany"]], "Hr-info": [["broadcastArea", "Hesse"], ["language", "German_language"]], "Hr1": [["broadcastArea", "Hesse"]], "Hr2-kultur": [["broadcastArea", "Hesse"], ["language", "German_language"]], "Hr3": [["broadcastArea", "Hesse"], ["language", "German_language"]], "Hr4": [["broadcastArea", "Hesse"], ["language", "German_language"]], "Klassik_Radio": [["broadcastArea", "Germany"], ["city", "Hamburg"], ["city", "Germany"], ["language", "German_language"], ["programmeFormat", "Film_score"], ["programmeFormat", "Lounge_music"], ["programmeFormat", "Classical_music"]], "LOHRO": [["city", "Rostock"]], "MDR_Aktuell": [["broadcastArea", "Saxony"], ["broadcastArea", "Saxony-Anhalt"], ["broadcastArea", "Thuringia"], ["language", "German_language"]], "MDR_Jump": [["broadcastArea", "Saxony"], ["broadcastArea", "Saxony-Anhalt"], ["broadcastArea", "Thuringia"], ["city", "Leipzig"], ["language", "German_language"]], "MDR_Klassik": [["broadcastArea", "Saxony"], ["broadcastArea", "Saxony-Anhalt"], ["broadcastArea", "Thuringia"], ["language", "German_language"]], "MDR_Kultur": [["broadcastArea", "Saxony"], ["broadcastArea", "Saxony-Anhalt"], ["broadcastArea", "Thuringia"], ["language", "German_language"]], "MDR_Schlagerwelt": [["broadcastArea", "Saxony"], ["broadcastArea", "Saxony-Anhalt"], ["broadcastArea", "Thuringia"], ["language", "German_language"]], "Mitteldeutscher_Rundfunk": [["country", "Germany"], ["keyPerson", "Karola_Wille"], ["locationCountry", "Germany"]], "Multicult.fm": [["regionServed", "Berlin"], ["service", "Radio"], ["service", "Internet_radio"]], "N-Joy": [["broadcastArea", "Schleswig-Holstein"], ["broadcastArea", "Hamburg"], ["broadcastArea", "Lower_Saxony"], ["broadcastArea", "Mecklenburg-Vorpommern"], ["owner", "Norddeutscher_Rundfunk"], ["programmeFormat", "Contemporary_hit_radio"]], "Puls_(German_radio_station)": [["broadcastArea", "Bavaria"], ["language", "German_language"]], "Radio_7": [["broadcastArea", "Baden-W\u00c3\u00bcrttemberg"], ["city", "Baden-W\u00c3\u00bcrttemberg"]], "Radio_Horeb": [["broadcastArea", "Oberallg\u00c3\u00a4u"], ["broadcastNetwork", "Radio_Maria"], ["city", "Balderschwang"]], "Radio_Humanit\u00c3\u00a9": [["broadcastArea", "France"], ["city", "Berlin"], ["programmeFormat", "Propaganda"]], "Radio_ffn": [["broadcastArea", "Hamburg"], ["broadcastArea", "Lower_Saxony"], ["broadcastArea", "Bremen_(state)"], ["programmeFormat", "Adult_contemporary_music"]], "Reboot.fm": [["broadcastArea", "Central_West_Berlin"], ["city", "Potsdam"], ["city", "Berlin"], ["programmeFormat", "Radio_art"], ["programmeFormat", "Community_radio"]], "Rundfunk_Berlin-Brandenburg": [["broadcastNetwork", "ARD_(broadcaster)"], ["country", "Germany"], ["keyPerson", "Patricia_Schlesinger"], ["locationCountry", "Germany"]], "SWR2_Archivradio": [["broadcastArea", "Internet"], ["city", "Baden-Baden"], ["owner", "S\u00c3\u00bcdwestrundfunk"]], "Saarl\u00c3\u00a4ndischer_Rundfunk": [["regionServed", "Saarland"], ["type", "Public_broadcasting"]], "Sputnik_(radio_station)": [["broadcastArea", "Saxony"], ["broadcastArea", "Saxony-Anhalt"], ["broadcastArea", "Thuringia"], ["language", "German_language"], ["programmeFormat", "Contemporary_hit_radio"]], "S\u00c3\u00bcdwestrundfunk": [["country", "Germany"], ["locationCountry", "Germany"]], "WDR_2": [["broadcastArea", "Europe"], ["broadcastArea", "Germany"], ["broadcastArea", "Internet"], ["broadcastArea", "DVB-C"], ["broadcastArea", "Digital_Audio_Broadcasting"], ["broadcastArea", "North_Rhine-Westphalia"], ["city", "Cologne"], ["owner", "Westdeutscher_Rundfunk"], ["programmeFormat", "Adult_contemporary_music"]], "WDR_3": [["broadcastArea", "North_Rhine-Westphalia"], ["language", "German_language"]], "WDR_4": [["broadcastArea", "North_Rhine-Westphalia"], ["language", "German_language"]], "WDR_5": [["broadcastArea", "North_Rhine-Westphalia"], ["language", "German_language"]], "WDR_Event": [["broadcastArea", "North_Rhine-Westphalia"], ["language", "German_language"]], "WDR_VERA": [["broadcastArea", "North_Rhine-Westphalia"], ["language", "German_language"], ["programmeFormat", "Traffic_reporting"]], "Westdeutscher_Rundfunk": [["broadcastNetwork", "ARD_(broadcaster)"], ["country", "Germany"], ["locationCountry", "Germany"]], "You_FM_(Germany)": [["broadcastArea", "Hesse"], ["language", "German_language"], ["programmeFormat", "Contemporary_hit_radio"]]}